u_unwrap3d-1.0.0.dist-info/licenses/LICENSE
unwrap3D/__init__.py
unwrap3D/Analysis_Functions/__init__.py
unwrap3D/Analysis_Functions/timeseries.py
unwrap3D/Analysis_Functions/topography.py
unwrap3D/Features/__init__.py
unwrap3D/Features/features.py
unwrap3D/Geometry/geometry.py
unwrap3D/Image_Functions/__init__.py
unwrap3D/Image_Functions/image.py
unwrap3D/Image_Functions/recolor.py
unwrap3D/Image_Functions/smoothn.py
unwrap3D/Mesh/__init__.py
unwrap3D/Mesh/meshtools.py
unwrap3D/Parameters/__init__.py
unwrap3D/Parameters/params.py
unwrap3D/Registration/__init__.py
unwrap3D/Registration/registration.py
unwrap3D/Segmentation/__init__.py
unwrap3D/Segmentation/segmentation.py
unwrap3D/Tracking/__init__.py
unwrap3D/Tracking/tracking.py
unwrap3D/Unzipping/__init__.py
unwrap3D/Unzipping/unzip.py
unwrap3D/Utility_Functions/__init__.py
unwrap3D/Utility_Functions/file_io.py
unwrap3D/Utility_Functions/stack.py
unwrap3D/Visualisation/__init__.py
unwrap3D/Visualisation/colors.py
unwrap3D/Visualisation/grid_img.py
unwrap3D/Visualisation/imshowpair.py
unwrap3D/Visualisation/plotting.py
unwrap3D/Visualisation/volume_img.py
u_unwrap3d-1.0.0.dist-info/METADATA
u_unwrap3d-1.0.0.dist-info/WHEEL
u_unwrap3d-1.0.0.dist-info/top_level.txt
u_unwrap3d-1.0.0.dist-info/RECORD
