Metadata-Version: 2.4
Name: u-Unwrap3D
Version: 1.0.0
Summary: Surface-guided computing of arbitrary 3D surfaces and volumes by bidirectional mapping to lower dimensions
Author-email: "Felix Y. Zhou" <felixzhou1@gmail.com>
License:                     GNU GENERAL PUBLIC LICENSE
Project-URL: Homepage, https://github.com/DanuserLab/u-unwrap3D
Project-URL: Issues, https://github.com/DanuserLab/u-unwrap3D/issues
Classifier: Intended Audience :: Developers
Classifier: Operating System :: POSIX :: Linux
Classifier: Operating System :: MacOS :: MacOS X
Classifier: Operating System :: Microsoft :: Windows
Classifier: Programming Language :: Python :: 3.9
Requires-Python: >=3.8
License-File: LICENSE
Requires-Dist: cgal>=5.5
Requires-Dist: libigl<2.6
Requires-Dist: pyacvd==0.2.9
Requires-Dist: trimesh[easy]
Requires-Dist: SimpleITK
Requires-Dist: opencv-contrib-python==4.5.*
Requires-Dist: point-cloud-utils
Requires-Dist: optimesh
Requires-Dist: scikit-image
Requires-Dist: scikit-learn
Requires-Dist: scipy
Requires-Dist: numpy<2.0
Requires-Dist: matplotlib
Requires-Dist: intel_openmp==2023.1.0
Requires-Dist: mkl==2023.1.0
Requires-Dist: pypardiso==0.4.*
Requires-Dist: tqdm
Requires-Dist: transforms3d
Requires-Dist: robust-laplacian
Requires-Dist: pygeodesic
Requires-Dist: potpourri3d
Requires-Dist: scikit-fmm
Requires-Dist: POT
Requires-Dist: hausdorff
Requires-Dist: numba
Requires-Dist: dipy
Dynamic: license-file
